dean_utils/__init__.py
dean_utils/polars_extras.py
dean_utils/utils/az_utils.py
dean_utils/utils/email_utility.py
dean_utils/utils/httpx.py
dean_utils-0.0.67.dist-info/licenses/LICENSE
dean_utils-0.0.67.dist-info/METADATA
dean_utils-0.0.67.dist-info/WHEEL
dean_utils-0.0.67.dist-info/top_level.txt
dean_utils-0.0.67.dist-info/RECORD
