Metadata-Version: 2.4
Name: dean_utils
Version: 0.0.67
Summary: various utils, functions, patches that I like
Author-email: Dean MacGregor <powertrading121@gmail.com>
Requires-Python: >=3.9
License-File: LICENSE
Requires-Dist: polars
Requires-Dist: pyarrow
Requires-Dist: azure-storage-blob
Requires-Dist: adlfs
Requires-Dist: fsspec
Requires-Dist: azure-storage-queue
Requires-Dist: python-multipart
Requires-Dist: azure-communication-email
Dynamic: license-file
